{"cameraMode":{"drawMode":0,"name":"Shaded","section":"Shading Mode"},"sceneLighting":true,"audioPlay":false,"sceneViewState":{"showFog":true,"showMaterialUpdate":false,"showSkybox":true,"showFlares":true,"showImageEffects":true,"showParticleSystems":true},"in2DMode":false,"pivot":{"x":0.22711841762065888,"y":1.4986824989318848,"z":-0.3873050808906555},"rotation":{"x":0.022038476541638376,"y":0.9740607738494873,"z":-0.10887347161769867,"w":0.1972496062517166},"size":1.4673364162445069,"orthographic":false}